<annotation>
	<folder>images</folder>
	<filename>Image229.jpg</filename>
	<path>/home/he/yolov5/VOCData/images/Image229.jpg</path>
	<source>
		<database>Unknown</database>
	</source>
	<size>
		<width>720</width>
		<height>1280</height>
		<depth>3</depth>
	</size>
	<segmented>0</segmented>
	<object>
		<name>X</name>
		<pose>Unspecified</pose>
		<truncated>0</truncated>
		<difficult>0</difficult>
		<bndbox>
			<xmin>2</xmin>
			<ymin>397</ymin>
			<xmax>320</xmax>
			<ymax>896</ymax>
		</bndbox>
	</object>
</annotation>
