{
  "version": "2.3.6",
  "flags": {},
  "shapes": [
    {
      "label": "3",
      "score": 0.9276148676872253,
      "points": [
        [
          698.8062286376953,
          881.1416015625
        ],
        [
          777.0913696289062,
          881.1416015625
        ],
        [
          777.0913696289062,
          954.2222900390625
        ],
        [
          698.8062286376953,
          954.2222900390625
        ]
      ],
      "group_id": null,
      "description": null,
      "difficult": false,
      "shape_type": "rectangle",
      "flags": {},
      "attributes": {}
    },
    {
      "label": "2",
      "score": 0.9261111617088318,
      "points": [
        [
          1561.34326171875,
          715.5155639648438
        ],
        [
          1636.2359619140625,
          715.5155639648438
        ],
        [
          1636.2359619140625,
          788.0482177734375
        ],
        [
          1561.34326171875,
          788.0482177734375
        ]
      ],
      "group_id": null,
      "description": null,
      "difficult": false,
      "shape_type": "rectangle",
      "flags": {},
      "attributes": {}
    },
    {
      "label": "3",
      "score": 0.9130136966705322,
      "points": [
        [
          873.6636657714844,
          585.8797302246094
        ],
        [
          946.1468811035156,
          585.8797302246094
        ],
        [
          946.1468811035156,
          657.3745422363281
        ],
        [
          873.6636657714844,
          657.3745422363281
        ]
      ],
      "group_id": null,
      "description": null,
      "difficult": false,
      "shape_type": "rectangle",
      "flags": {},
      "attributes": {}
    },
    {
      "label": "2",
      "score": 0.9083521962165833,
      "points": [
        [
          1316.0225830078125,
          545.1787719726562
        ],
        [
          1389.9505004882812,
          545.1787719726562
        ],
        [
          1389.9505004882812,
          617.4596557617188
        ],
        [
          1316.0225830078125,
          617.4596557617188
        ]
      ],
      "group_id": null,
      "description": null,
      "difficult": false,
      "shape_type": "rectangle",
      "flags": {},
      "attributes": {}
    },
    {
      "label": "1",
      "score": 0.8581424355506897,
      "points": [
        [
          1241.816162109375,
          752.0917053222656
        ],
        [
          1309.6424560546875,
          752.0917053222656
        ],
        [
          1309.6424560546875,
          814.1781921386719
        ],
        [
          1241.816162109375,
          814.1781921386719
        ]
      ],
      "group_id": null,
      "description": null,
      "difficult": false,
      "shape_type": "rectangle",
      "flags": {},
      "attributes": {}
    },
    {
      "label": "1",
      "score": 0.7936726808547974,
      "points": [
        [
          1661.7702026367188,
          332.45562744140625
        ],
        [
          1736.4006958007812,
          332.45562744140625
        ],
        [
          1736.4006958007812,
          401.9498291015625
        ],
        [
          1661.7702026367188,
          401.9498291015625
        ]
      ],
      "group_id": null,
      "description": null,
      "difficult": false,
      "shape_type": "rectangle",
      "flags": {},
      "attributes": {}
    }
  ],
  "imagePath": "..\\images\\Image504.jpg",
  "imageData": null,
  "imageHeight": 1080,
  "imageWidth": 1920
}