{
  "version": "2.3.6",
  "flags": {},
  "shapes": [
    {
      "label": "3",
      "score": 0.742030680179596,
      "points": [
        [
          866.0602111816406,
          313.1666564941406
        ],
        [
          904.3959045410156,
          313.1666564941406
        ],
        [
          904.3959045410156,
          350.9476318359375
        ],
        [
          866.0602111816406,
          350.9476318359375
        ]
      ],
      "group_id": null,
      "description": null,
      "difficult": false,
      "shape_type": "rectangle",
      "flags": {},
      "attributes": {}
    },
    {
      "label": "3",
      "score": 0.3519178032875061,
      "points": [
        [
          816.9549865722656,
          109.82945251464844
        ],
        [
          856.6394348144531,
          109.82945251464844
        ],
        [
          856.6394348144531,
          147.7137908935547
        ],
        [
          816.9549865722656,
          147.7137908935547
        ]
      ],
      "group_id": null,
      "description": null,
      "difficult": false,
      "shape_type": "rectangle",
      "flags": {},
      "attributes": {}
    },
    {
      "label": "1",
      "score": null,
      "points": [
        [
          1033.469387755102,
          18.571428571428626
        ],
        [
          1084.4897959183672,
          18.571428571428626
        ],
        [
          1084.4897959183672,
          67.55102040816332
        ],
        [
          1033.469387755102,
          67.55102040816332
        ]
      ],
      "group_id": null,
      "description": "",
      "difficult": false,
      "shape_type": "rectangle",
      "flags": {},
      "attributes": {}
    }
  ],
  "imagePath": "Image666.jpg",
  "imageData": null,
  "imageHeight": 1080,
  "imageWidth": 1920,
  "text": ""
}