{
  "version": "2.3.6",
  "flags": {},
  "shapes": [
    {
      "label": "3",
      "score": 0.9502708911895752,
      "points": [
        [
          948.7351684570312,
          733.6333923339844
        ],
        [
          1028.9027709960938,
          733.6333923339844
        ],
        [
          1028.9027709960938,
          813.4210510253906
        ],
        [
          948.7351684570312,
          813.4210510253906
        ]
      ],
      "group_id": null,
      "description": null,
      "difficult": false,
      "shape_type": "rectangle",
      "flags": {},
      "attributes": {}
    },
    {
      "label": "2",
      "score": 0.9501122832298279,
      "points": [
        [
          378.17996978759766,
          386.4289855957031
        ],
        [
          455.8728332519531,
          386.4289855957031
        ],
        [
          455.8728332519531,
          463.3067321777344
        ],
        [
          378.17996978759766,
          463.3067321777344
        ]
      ],
      "group_id": null,
      "description": null,
      "difficult": false,
      "shape_type": "rectangle",
      "flags": {},
      "attributes": {}
    },
    {
      "label": "2",
      "score": 0.9390863180160522,
      "points": [
        [
          837.711181640625,
          584.7038269042969
        ],
        [
          913.3807983398438,
          584.7038269042969
        ],
        [
          913.3807983398438,
          659.1250305175781
        ],
        [
          837.711181640625,
          659.1250305175781
        ]
      ],
      "group_id": null,
      "description": null,
      "difficult": false,
      "shape_type": "rectangle",
      "flags": {},
      "attributes": {}
    },
    {
      "label": "3",
      "score": 0.9346044659614563,
      "points": [
        [
          1069.7981872558594,
          391.55767822265625
        ],
        [
          1145.7157287597656,
          391.55767822265625
        ],
        [
          1145.7157287597656,
          469.28778076171875
        ],
        [
          1069.7981872558594,
          469.28778076171875
        ]
      ],
      "group_id": null,
      "description": null,
      "difficult": false,
      "shape_type": "rectangle",
      "flags": {},
      "attributes": {}
    },
    {
      "label": "1",
      "score": 0.9304189682006836,
      "points": [
        [
          980.9263000488281,
          256.97850036621094
        ],
        [
          1050.3564147949219,
          256.97850036621094
        ],
        [
          1050.3564147949219,
          325.8809051513672
        ],
        [
          980.9263000488281,
          325.8809051513672
        ]
      ],
      "group_id": null,
      "description": null,
      "difficult": false,
      "shape_type": "rectangle",
      "flags": {},
      "attributes": {}
    },
    {
      "label": "1",
      "score": 0.9132404327392578,
      "points": [
        [
          948.8888854980469,
          526.962158203125
        ],
        [
          1027.7624816894531,
          526.962158203125
        ],
        [
          1027.7624816894531,
          604.370361328125
        ],
        [
          948.8888854980469,
          604.370361328125
        ]
      ],
      "group_id": null,
      "description": null,
      "difficult": false,
      "shape_type": "rectangle",
      "flags": {},
      "attributes": {}
    }
  ],
  "imagePath": "..\\images\\Image60.jpg",
  "imageData": null,
  "imageHeight": 1080,
  "imageWidth": 1920
}