{
  "version": "2.3.6",
  "flags": {},
  "shapes": [
    {
      "label": "1",
      "score": 0.9319772124290466,
      "points": [
        [
          1226.0342102050781,
          360.9993896484375
        ],
        [
          1279.4343566894531,
          360.9993896484375
        ],
        [
          1279.4343566894531,
          414.308349609375
        ],
        [
          1226.0342102050781,
          414.308349609375
        ]
      ],
      "group_id": null,
      "description": null,
      "difficult": false,
      "shape_type": "rectangle",
      "flags": {},
      "attributes": {}
    },
    {
      "label": "3",
      "score": 0.9276342391967773,
      "points": [
        [
          1085.4560852050781,
          553.3097534179688
        ],
        [
          1134.3959655761719,
          553.3097534179688
        ],
        [
          1134.3959655761719,
          601.4468994140625
        ],
        [
          1085.4560852050781,
          601.4468994140625
        ]
      ],
      "group_id": null,
      "description": null,
      "difficult": false,
      "shape_type": "rectangle",
      "flags": {},
      "attributes": {}
    },
    {
      "label": "3",
      "score": 0.9247840642929077,
      "points": [
        [
          878.3366088867188,
          494.3844909667969
        ],
        [
          927.5555419921875,
          494.3844909667969
        ],
        [
          927.5555419921875,
          542.7552795410156
        ],
        [
          878.3366088867188,
          542.7552795410156
        ]
      ],
      "group_id": null,
      "description": null,
      "difficult": false,
      "shape_type": "rectangle",
      "flags": {},
      "attributes": {}
    },
    {
      "label": "1",
      "score": 0.9225453734397888,
      "points": [
        [
          1134.9701843261719,
          379.815673828125
        ],
        [
          1187.2942199707031,
          379.815673828125
        ],
        [
          1187.2942199707031,
          431.50469970703125
        ],
        [
          1134.9701843261719,
          431.50469970703125
        ]
      ],
      "group_id": null,
      "description": null,
      "difficult": false,
      "shape_type": "rectangle",
      "flags": {},
      "attributes": {}
    },
    {
      "label": "2",
      "score": 0.9221330881118774,
      "points": [
        [
          1388.6567687988281,
          191.87425231933594
        ],
        [
          1440.7191467285156,
          191.87425231933594
        ],
        [
          1440.7191467285156,
          243.6240692138672
        ],
        [
          1388.6567687988281,
          243.6240692138672
        ]
      ],
      "group_id": null,
      "description": null,
      "difficult": false,
      "shape_type": "rectangle",
      "flags": {},
      "attributes": {}
    },
    {
      "label": "2",
      "score": 0.8338513374328613,
      "points": [
        [
          1000.8179626464844,
          318.45460510253906
        ],
        [
          1042.8366394042969,
          318.45460510253906
        ],
        [
          1042.8366394042969,
          359.6309509277344
        ],
        [
          1000.8179626464844,
          359.6309509277344
        ]
      ],
      "group_id": null,
      "description": null,
      "difficult": false,
      "shape_type": "rectangle",
      "flags": {},
      "attributes": {}
    }
  ],
  "imagePath": "..\\images\\Image121.jpg",
  "imageData": null,
  "imageHeight": 1080,
  "imageWidth": 1920
}