{
  "version": "2.3.6",
  "flags": {},
  "shapes": [
    {
      "label": "2",
      "score": 0.9231728911399841,
      "points": [
        [
          540.7827758789062,
          500.5994567871094
        ],
        [
          594.9798889160156,
          500.5994567871094
        ],
        [
          594.9798889160156,
          552.6089172363281
        ],
        [
          540.7827758789062,
          552.6089172363281
        ]
      ],
      "group_id": null,
      "description": null,
      "difficult": false,
      "shape_type": "rectangle",
      "flags": {},
      "attributes": {}
    },
    {
      "label": "3",
      "score": 0.8966516852378845,
      "points": [
        [
          219.49413299560547,
          369.542724609375
        ],
        [
          267.80834197998047,
          369.542724609375
        ],
        [
          267.80834197998047,
          417.6112060546875
        ],
        [
          219.49413299560547,
          417.6112060546875
        ]
      ],
      "group_id": null,
      "description": null,
      "difficult": false,
      "shape_type": "rectangle",
      "flags": {},
      "attributes": {}
    },
    {
      "label": "2",
      "score": 0.873906672000885,
      "points": [
        [
          645.9024810791016,
          704.8333740234375
        ],
        [
          697.0106048583984,
          704.8333740234375
        ],
        [
          697.0106048583984,
          754.3405151367188
        ],
        [
          645.9024810791016,
          754.3405151367188
        ]
      ],
      "group_id": null,
      "description": null,
      "difficult": false,
      "shape_type": "rectangle",
      "flags": {},
      "attributes": {}
    },
    {
      "label": "1",
      "score": 0.8603481650352478,
      "points": [
        [
          848.2183227539062,
          472.89642333984375
        ],
        [
          903.3751831054688,
          472.89642333984375
        ],
        [
          903.3751831054688,
          527.2307739257812
        ],
        [
          848.2183227539062,
          527.2307739257812
        ]
      ],
      "group_id": null,
      "description": null,
      "difficult": false,
      "shape_type": "rectangle",
      "flags": {},
      "attributes": {}
    },
    {
      "label": "1",
      "score": 0.8411027193069458,
      "points": [
        [
          408.0923309326172,
          606.9684448242188
        ],
        [
          470.70314025878906,
          606.9684448242188
        ],
        [
          470.70314025878906,
          664.8310546875
        ],
        [
          408.0923309326172,
          664.8310546875
        ]
      ],
      "group_id": null,
      "description": null,
      "difficult": false,
      "shape_type": "rectangle",
      "flags": {},
      "attributes": {}
    },
    {
      "label": "3",
      "score": 0.8295559287071228,
      "points": [
        [
          0.0,
          505.6549072265625
        ],
        [
          37.4115514755249,
          505.6549072265625
        ],
        [
          37.4115514755249,
          560.3472290039062
        ],
        [
          0.0,
          560.3472290039062
        ]
      ],
      "group_id": null,
      "description": null,
      "difficult": false,
      "shape_type": "rectangle",
      "flags": {},
      "attributes": {}
    }
  ],
  "imagePath": "..\\images\\Image635.jpg",
  "imageData": null,
  "imageHeight": 1080,
  "imageWidth": 1920
}