{
  "version": "2.3.6",
  "flags": {},
  "shapes": [
    {
      "label": "2",
      "score": 0.9551315903663635,
      "points": [
        [
          1623.7137451171875,
          700.7351989746094
        ],
        [
          1751.9857177734375,
          700.7351989746094
        ],
        [
          1751.9857177734375,
          830.4059143066406
        ],
        [
          1623.7137451171875,
          830.4059143066406
        ]
      ],
      "group_id": null,
      "description": null,
      "difficult": false,
      "shape_type": "rectangle",
      "flags": {},
      "attributes": {}
    },
    {
      "label": "3",
      "score": 0.9521311521530151,
      "points": [
        [
          1806.7305908203125,
          454.8838806152344
        ],
        [
          1920.0,
          454.8838806152344
        ],
        [
          1920.0,
          579.5748596191406
        ],
        [
          1806.7305908203125,
          579.5748596191406
        ]
      ],
      "group_id": null,
      "description": null,
      "difficult": false,
      "shape_type": "rectangle",
      "flags": {},
      "attributes": {}
    },
    {
      "label": "3",
      "score": 0.9266489744186401,
      "points": [
        [
          1347.4615173339844,
          679.9787292480469
        ],
        [
          1484.8418884277344,
          679.9787292480469
        ],
        [
          1484.8418884277344,
          820.3772277832031
        ],
        [
          1347.4615173339844,
          820.3772277832031
        ]
      ],
      "group_id": null,
      "description": null,
      "difficult": false,
      "shape_type": "rectangle",
      "flags": {},
      "attributes": {}
    },
    {
      "label": "2",
      "score": 0.9078088998794556,
      "points": [
        [
          1804.2896118164062,
          972.3469848632812
        ],
        [
          1918.2046508789062,
          972.3469848632812
        ],
        [
          1918.2046508789062,
          1080.0
        ],
        [
          1804.2896118164062,
          1080.0
        ]
      ],
      "group_id": null,
      "description": null,
      "difficult": false,
      "shape_type": "rectangle",
      "flags": {},
      "attributes": {}
    },
    {
      "label": "1",
      "score": 0.8125032782554626,
      "points": [
        [
          971.7214903539539,
          548.6732177734373
        ],
        [
          1113.061224489796,
          548.6732177734373
        ],
        [
          1113.061224489796,
          677.7551020408164
        ],
        [
          971.7214903539539,
          677.7551020408164
        ]
      ],
      "group_id": null,
      "description": null,
      "difficult": false,
      "shape_type": "rectangle",
      "flags": {},
      "attributes": {}
    }
  ],
  "imagePath": "Image1132.jpg",
  "imageData": null,
  "imageHeight": 1080,
  "imageWidth": 1920,
  "text": ""
}