{
  "version": "2.3.6",
  "flags": {},
  "shapes": [
    {
      "label": "1",
      "score": 0.9169738292694092,
      "points": [
        [
          660.3179626464844,
          129.90921020507812
        ],
        [
          755.09326171875,
          129.90921020507812
        ],
        [
          755.09326171875,
          218.72470092773438
        ],
        [
          660.3179626464844,
          218.72470092773438
        ]
      ],
      "group_id": null,
      "description": null,
      "difficult": false,
      "shape_type": "rectangle",
      "flags": {},
      "attributes": {}
    },
    {
      "label": "2",
      "score": 0.9109939336776733,
      "points": [
        [
          1009.2713012695312,
          292.98358154296875
        ],
        [
          1091.7811889648438,
          292.98358154296875
        ],
        [
          1091.7811889648438,
          371.36553955078125
        ],
        [
          1009.2713012695312,
          371.36553955078125
        ]
      ],
      "group_id": null,
      "description": null,
      "difficult": false,
      "shape_type": "rectangle",
      "flags": {},
      "attributes": {}
    },
    {
      "label": "2",
      "score": 0.3346388041973114,
      "points": [
        [
          860.5995483398438,
          0.748443603515625
        ],
        [
          961.3244018554688,
          0.748443603515625
        ],
        [
          961.3244018554688,
          59.15863037109375
        ],
        [
          860.5995483398438,
          59.15863037109375
        ]
      ],
      "group_id": null,
      "description": null,
      "difficult": false,
      "shape_type": "rectangle",
      "flags": {},
      "attributes": {}
    }
  ],
  "imagePath": "..\\images\\Image491.jpg",
  "imageData": null,
  "imageHeight": 1080,
  "imageWidth": 1920
}