{
  "version": "2.3.6",
  "flags": {},
  "shapes": [
    {
      "label": "3",
      "score": null,
      "points": [
        [
          1882.4489795918366,
          735.9183673469388
        ],
        [
          1919.0,
          735.9183673469388
        ],
        [
          1919.0,
          785
        ],
        [
          1882.4489795918366,
          785
        ]
      ],
      "group_id": null,
      "description": "",
      "difficult": false,
      "shape_type": "rectangle",
      "flags": {},
      "attributes": {}
    }
  ],
  "imagePath": "Image2613.jpg",
  "imageData": null,
  "imageHeight": 1080,
  "imageWidth": 1920,
  "text": ""
}