{
  "version": "2.3.6",
  "flags": {},
  "shapes": [
    {
      "label": "3",
      "score": 0.8763104677200317,
      "points": [
        [
          833.3374328613281,
          746.7739562988281
        ],
        [
          865.4363708496094,
          746.7739562988281
        ],
        [
          865.4363708496094,
          778.4107360839844
        ],
        [
          833.3374328613281,
          778.4107360839844
        ]
      ],
      "group_id": null,
      "description": "",
      "difficult": false,
      "shape_type": "rectangle",
      "flags": {},
      "attributes": {}
    },
    {
      "label": "3",
      "score": 0.8253348469734192,
      "points": [
        [
          644.9146728515625,
          687.3958740234375
        ],
        [
          682.9875183105469,
          687.3958740234375
        ],
        [
          682.9875183105469,
          724.4221801757812
        ],
        [
          644.9146728515625,
          724.4221801757812
        ]
      ],
      "group_id": null,
      "description": null,
      "difficult": false,
      "shape_type": "rectangle",
      "flags": {},
      "attributes": {}
    },
    {
      "label": "2",
      "score": 0.8199805021286011,
      "points": [
        [
          901.9324035644531,
          814.8427734375
        ],
        [
          938.5311584472656,
          814.8427734375
        ],
        [
          938.5311584472656,
          851.559814453125
        ],
        [
          901.9324035644531,
          851.559814453125
        ]
      ],
      "group_id": null,
      "description": null,
      "difficult": false,
      "shape_type": "rectangle",
      "flags": {},
      "attributes": {}
    },
    {
      "label": "1",
      "score": 0.6929313540458679,
      "points": [
        [
          908.9546813964844,
          661.604736328125
        ],
        [
          940.8210754394531,
          661.604736328125
        ],
        [
          940.8210754394531,
          692.5980834960938
        ],
        [
          908.9546813964844,
          692.5980834960938
        ]
      ],
      "group_id": null,
      "description": null,
      "difficult": false,
      "shape_type": "rectangle",
      "flags": {},
      "attributes": {}
    },
    {
      "label": "2",
      "score": 0.5851050019264221,
      "points": [
        [
          1045.0640258789062,
          771.8637084960938
        ],
        [
          1079.534912109375,
          771.8637084960938
        ],
        [
          1079.534912109375,
          805.4196166992188
        ],
        [
          1045.0640258789062,
          805.4196166992188
        ]
      ],
      "group_id": null,
      "description": null,
      "difficult": false,
      "shape_type": "rectangle",
      "flags": {},
      "attributes": {}
    },
    {
      "label": "1",
      "score": 0.6929313540458679,
      "points": [
        [
          954.356980247059,
          745.5127823051365
        ],
        [
          986.2233742900278,
          745.5127823051365
        ],
        [
          986.2233742900278,
          776.5061294731053
        ],
        [
          954.356980247059,
          776.5061294731053
        ]
      ],
      "group_id": null,
      "description": null,
      "difficult": false,
      "shape_type": "rectangle",
      "flags": {},
      "attributes": {}
    }
  ],
  "imagePath": "Image902.jpg",
  "imageData": null,
  "imageHeight": 1080,
  "imageWidth": 1920,
  "text": ""
}