{
  "version": "2.3.6",
  "flags": {},
  "shapes": [
    {
      "label": "3",
      "score": 0.9444219470024109,
      "points": [
        [
          543.6743316650391,
          696.5735778808594
        ],
        [
          625.7150115966797,
          696.5735778808594
        ],
        [
          625.7150115966797,
          778.4929504394531
        ],
        [
          543.6743316650391,
          778.4929504394531
        ]
      ],
      "group_id": null,
      "description": null,
      "difficult": false,
      "shape_type": "rectangle",
      "flags": {},
      "attributes": {}
    },
    {
      "label": "1",
      "score": 0.930687427520752,
      "points": [
        [
          1546.1237182617188,
          925.3338317871094
        ],
        [
          1643.5640258789062,
          925.3338317871094
        ],
        [
          1643.5640258789062,
          1016.9072570800781
        ],
        [
          1546.1237182617188,
          1016.9072570800781
        ]
      ],
      "group_id": null,
      "description": null,
      "difficult": false,
      "shape_type": "rectangle",
      "flags": {},
      "attributes": {}
    },
    {
      "label": "3",
      "score": 0.9231879711151123,
      "points": [
        [
          152.75706481933594,
          895.3058166503906
        ],
        [
          252.33023071289062,
          895.3058166503906
        ],
        [
          252.33023071289062,
          989.9017639160156
        ],
        [
          152.75706481933594,
          989.9017639160156
        ]
      ],
      "group_id": null,
      "description": null,
      "difficult": false,
      "shape_type": "rectangle",
      "flags": {},
      "attributes": {}
    },
    {
      "label": "2",
      "score": 0.9095489382743835,
      "points": [
        [
          1046.6053161621094,
          936.227783203125
        ],
        [
          1138.7727355957031,
          936.227783203125
        ],
        [
          1138.7727355957031,
          1030.020263671875
        ],
        [
          1046.6053161621094,
          1030.020263671875
        ]
      ],
      "group_id": null,
      "description": null,
      "difficult": false,
      "shape_type": "rectangle",
      "flags": {},
      "attributes": {}
    }
  ],
  "imagePath": "..\\images\\Image481.jpg",
  "imageData": null,
  "imageHeight": 1080,
  "imageWidth": 1920
}