{
  "version": "2.3.6",
  "flags": {},
  "shapes": [
    {
      "label": "3",
      "score": 0.9325248599052429,
      "points": [
        [
          1085.0843811035156,
          552.6414184570312
        ],
        [
          1131.8993225097656,
          552.6414184570312
        ],
        [
          1131.8993225097656,
          599.200927734375
        ],
        [
          1085.0843811035156,
          599.200927734375
        ]
      ],
      "group_id": null,
      "description": null,
      "difficult": false,
      "shape_type": "rectangle",
      "flags": {},
      "attributes": {}
    },
    {
      "label": "1",
      "score": 0.9323007464408875,
      "points": [
        [
          1112.0585632324219,
          373.0855407714844
        ],
        [
          1166.3222351074219,
          373.0855407714844
        ],
        [
          1166.3222351074219,
          427.2908020019531
        ],
        [
          1112.0585632324219,
          427.2908020019531
        ]
      ],
      "group_id": null,
      "description": null,
      "difficult": false,
      "shape_type": "rectangle",
      "flags": {},
      "attributes": {}
    },
    {
      "label": "3",
      "score": 0.9284915924072266,
      "points": [
        [
          872.7735900878906,
          518.5664978027344
        ],
        [
          918.1139831542969,
          518.5664978027344
        ],
        [
          918.1139831542969,
          563.7889709472656
        ],
        [
          872.7735900878906,
          563.7889709472656
        ]
      ],
      "group_id": null,
      "description": null,
      "difficult": false,
      "shape_type": "rectangle",
      "flags": {},
      "attributes": {}
    },
    {
      "label": "2",
      "score": 0.9189514517784119,
      "points": [
        [
          1342.9237060546875,
          156.93685913085938
        ],
        [
          1398.9876708984375,
          156.93685913085938
        ],
        [
          1398.9876708984375,
          210.1124267578125
        ],
        [
          1342.9237060546875,
          210.1124267578125
        ]
      ],
      "group_id": null,
      "description": null,
      "difficult": false,
      "shape_type": "rectangle",
      "flags": {},
      "attributes": {}
    },
    {
      "label": "1",
      "score": 0.9167619347572327,
      "points": [
        [
          1201.0337219238281,
          344.71124267578125
        ],
        [
          1254.5367736816406,
          344.71124267578125
        ],
        [
          1254.5367736816406,
          398.3887939453125
        ],
        [
          1201.0337219238281,
          398.3887939453125
        ]
      ],
      "group_id": null,
      "description": null,
      "difficult": false,
      "shape_type": "rectangle",
      "flags": {},
      "attributes": {}
    },
    {
      "label": "2",
      "score": 0.8954004645347595,
      "points": [
        [
          970.3970947265625,
          327.8525848388672
        ],
        [
          1015.0751953125,
          327.8525848388672
        ],
        [
          1015.0751953125,
          372.1834716796875
        ],
        [
          970.3970947265625,
          372.1834716796875
        ]
      ],
      "group_id": null,
      "description": null,
      "difficult": false,
      "shape_type": "rectangle",
      "flags": {},
      "attributes": {}
    }
  ],
  "imagePath": "..\\images\\Image122.jpg",
  "imageData": null,
  "imageHeight": 1080,
  "imageWidth": 1920
}