{
  "version": "2.3.6",
  "flags": {},
  "shapes": [
    {
      "label": "3",
      "score": 0.9233721494674683,
      "points": [
        [
          1061.7908020019531,
          30.034103393554688
        ],
        [
          1120.3796081542969,
          30.034103393554688
        ],
        [
          1120.3796081542969,
          87.33860778808594
        ],
        [
          1061.7908020019531,
          87.33860778808594
        ]
      ],
      "group_id": null,
      "description": null,
      "difficult": false,
      "shape_type": "rectangle",
      "flags": {},
      "attributes": {}
    },
    {
      "label": "2",
      "score": 0.9193838238716125,
      "points": [
        [
          910.8945922851562,
          26.240615844726562
        ],
        [
          956.7894287109375,
          26.240615844726562
        ],
        [
          956.7894287109375,
          72.44947814941406
        ],
        [
          910.8945922851562,
          72.44947814941406
        ]
      ],
      "group_id": null,
      "description": null,
      "difficult": false,
      "shape_type": "rectangle",
      "flags": {},
      "attributes": {}
    },
    {
      "label": "1",
      "score": 0.9121832251548767,
      "points": [
        [
          918.7043151855469,
          155.8169403076172
        ],
        [
          974.5881042480469,
          155.8169403076172
        ],
        [
          974.5881042480469,
          213.7789764404297
        ],
        [
          918.7043151855469,
          213.7789764404297
        ]
      ],
      "group_id": null,
      "description": null,
      "difficult": false,
      "shape_type": "rectangle",
      "flags": {},
      "attributes": {}
    },
    {
      "label": "1",
      "score": 0.5374376773834229,
      "points": [
        [
          1059.9674098638839,
          210.9154847698447
        ],
        [
          1114.469851270134,
          210.9154847698447
        ],
        [
          1114.469851270134,
          263.0084413128135
        ],
        [
          1059.9674098638839,
          263.0084413128135
        ]
      ],
      "group_id": null,
      "description": null,
      "difficult": false,
      "shape_type": "rectangle",
      "flags": {},
      "attributes": {}
    },
    {
      "label": "2",
      "score": 0.9193838238716125,
      "points": [
        [
          787.4378021616994,
          221.30234423978828
        ],
        [
          841.9753086419752,
          221.30234423978828
        ],
        [
          841.9753086419752,
          275.1851851851852
        ],
        [
          787.4378021616994,
          275.1851851851852
        ]
      ],
      "group_id": null,
      "description": null,
      "difficult": false,
      "shape_type": "rectangle",
      "flags": {},
      "attributes": {}
    }
  ],
  "imagePath": "Image885.jpg",
  "imageData": null,
  "imageHeight": 1080,
  "imageWidth": 1920,
  "text": ""
}