{
  "version": "2.3.6",
  "flags": {},
  "shapes": [
    {
      "label": "2",
      "score": 0.9367472529411316,
      "points": [
        [
          1375.2389831542969,
          652.0083618164062
        ],
        [
          1425.1322937011719,
          652.0083618164062
        ],
        [
          1425.1322937011719,
          699.83642578125
        ],
        [
          1375.2389831542969,
          699.83642578125
        ]
      ],
      "group_id": null,
      "description": null,
      "difficult": false,
      "shape_type": "rectangle",
      "flags": {},
      "attributes": {}
    },
    {
      "label": "1",
      "score": 0.9122021198272705,
      "points": [
        [
          1456.1187744140625,
          629.4252319335938
        ],
        [
          1507.1683959960938,
          629.4252319335938
        ],
        [
          1507.1683959960938,
          678.9102172851562
        ],
        [
          1456.1187744140625,
          678.9102172851562
        ]
      ],
      "group_id": null,
      "description": null,
      "difficult": false,
      "shape_type": "rectangle",
      "flags": {},
      "attributes": {}
    },
    {
      "label": "3",
      "score": 0.9076083898544312,
      "points": [
        [
          1137.9891357421875,
          370.5790100097656
        ],
        [
          1182.6207275390625,
          370.5790100097656
        ],
        [
          1182.6207275390625,
          413.0852966308594
        ],
        [
          1137.9891357421875,
          413.0852966308594
        ]
      ],
      "group_id": null,
      "description": null,
      "difficult": false,
      "shape_type": "rectangle",
      "flags": {},
      "attributes": {}
    },
    {
      "label": "2",
      "score": 0.9007726907730103,
      "points": [
        [
          1541.8302612304688,
          501.8253479003906
        ],
        [
          1587.0210571289062,
          501.8253479003906
        ],
        [
          1587.0210571289062,
          545.0387878417969
        ],
        [
          1541.8302612304688,
          545.0387878417969
        ]
      ],
      "group_id": null,
      "description": null,
      "difficult": false,
      "shape_type": "rectangle",
      "flags": {},
      "attributes": {}
    },
    {
      "label": "3",
      "score": 0.893595814704895,
      "points": [
        [
          924.0062255859375,
          566.5130310058594
        ],
        [
          970.9163818359375,
          566.5130310058594
        ],
        [
          970.9163818359375,
          610.4806823730469
        ],
        [
          924.0062255859375,
          610.4806823730469
        ]
      ],
      "group_id": null,
      "description": null,
      "difficult": false,
      "shape_type": "rectangle",
      "flags": {},
      "attributes": {}
    },
    {
      "label": "1",
      "score": 0.8379495143890381,
      "points": [
        [
          1427.4819030761719,
          542.5252990722656
        ],
        [
          1471.0236511230469,
          542.5252990722656
        ],
        [
          1471.0236511230469,
          583.3012390136719
        ],
        [
          1427.4819030761719,
          583.3012390136719
        ]
      ],
      "group_id": null,
      "description": null,
      "difficult": false,
      "shape_type": "rectangle",
      "flags": {},
      "attributes": {}
    }
  ],
  "imagePath": "..\\images\\Image400.jpg",
  "imageData": null,
  "imageHeight": 1080,
  "imageWidth": 1920
}